crashalyser/.gitignore
crashalyser/__init__.py
crashalyser/__main__.py
crashalyser/cli.py
crashalyser-0.9.0.dist-info/entry_points.txt
crashalyser-0.9.0.dist-info/WHEEL
crashalyser-0.9.0.dist-info/METADATA
crashalyser-0.9.0.dist-info/RECORD
