Metadata-Version: 2.1
Name: crashalyser
Version: 0.9.0
Summary: Automatically analyse and record via email or file backtraces from core dumps
Author: Ross Cousens
Author-email: rcousens@kixeye.com
Requires-Python: >=3.6,<4.0
Classifier: Programming Language :: Python :: 3
Classifier: Programming Language :: Python :: 3.6
Classifier: Programming Language :: Python :: 3.7
Classifier: Programming Language :: Python :: 3.8
Requires-Dist: click (>=7.1.2,<8.0.0)
Requires-Dist: croniter (>=0.3.34,<0.4.0)
Requires-Dist: python-crontab (>=2.5.1,<3.0.0)
